datasette_total_page_time/__init__.py
datasette_total_page_time-0.1.dist-info/LICENSE
datasette_total_page_time-0.1.dist-info/METADATA
datasette_total_page_time-0.1.dist-info/WHEEL
datasette_total_page_time-0.1.dist-info/entry_points.txt
datasette_total_page_time-0.1.dist-info/top_level.txt
datasette_total_page_time-0.1.dist-info/RECORD
