Metadata-Version: 2.1
Name: datasette-total-page-time
Version: 0.1
Summary: Add a note to the Datasette footer measuring the total page load time
Home-page: https://github.com/simonw/datasette-total-page-time
Author: Simon Willison
License: Apache License, Version 2.0
Project-URL: Issues, https://github.com/simonw/datasette-total-page-time/issues
Project-URL: CI, https://github.com/simonw/datasette-total-page-time/actions
Project-URL: Changelog, https://github.com/simonw/datasette-total-page-time/releases
Platform: UNKNOWN
Classifier: Framework :: Datasette
Classifier: License :: OSI Approved :: Apache Software License
Requires-Python: >=3.7
License-File: LICENSE
Requires-Dist: datasette
Provides-Extra: test
Requires-Dist: pytest ; extra == 'test'
Requires-Dist: pytest-asyncio ; extra == 'test'
